[
  {
    "id": "2018-0025/2018",
    "year": 2018,
    "expediente": "0025/2018",
    "titulo": "Informe 0025/2018",
    "tipo": "incidente",
    "tipo_suceso": "incidente",
    "gravedad": "fatal",
    "fecha_suceso": "2018-07-01",
    "ubicacion": {
      "estacion": "PEDRALBA (ZAMORA)",
      "provincia": "Zamora",
      "lat": 39.55,
      "lng": -0.7167
    },
    "entidades": [
      "ADIF",
      "Renfe Viajeros"
    ],
    "consecuencias": {
      "victimas_mortales": 0,
      "heridos": 0,
      "danos_materiales": true
    },
    "analisis": {
      "resumen": "MINISTERIO\nTRANSPORTES,\nMOVILIDAD\nAGENDA URBANA\nSUBSECRETARÍA\nInvestigación del incidente\nnº 0025/2018 ocurrido el 01.07.2018\n200421-180701-IF_CIAF\n1. RESUMEN\nEl incidente por fallo en las instalaciones de seguridad, tiene lugar el día 1 de julio de 2018, a las 20:02\nhoras, en la estación de Pedralba (Zamora), pk 113+475 de la línea 822 Zamora - A Coruña, estando la\nestación con mando central.\nEl tren Alvia 258, de RENFE VIAJEROS, procedente de Madrid Chamartín con destino Pontevedra, tiene\nprevisto realizar el cruce en la estación de Pedralba con el tren 253 también de RENFE VIAJEROS,\nprocedente de Pontevedra con destino Madrid Chamartín, según itinerario que establece el puesto de\nmando de Ourense conforme la Consigna A1275 de esta estación.\nEl mal funcionamiento del enclavamiento se pro",
      "descripcion": "2. HECHOS INMEDIATOS DEL SUCESO. ................................................................................................................ 9\n2.1. SUCESO. ............................................................................................................................. 9\n2.1.1. Datos .................................................................................................................................. 9\n2.1.2. Descripción del suceso ......................................................................................................... 9\n2.1.3. Decisión de abrir la investigación ........................................................................................ 13\n2.2. CIRCUNSTANCIAS DEL SUCESO ...................................................................................... 13\n2.2.1. Personal Ferroviario implicado ............................................................................................ 13\n2.2.2. Material rodante .............."
    },
    "conclusiones": [
      "Investigación del incidente",
      "nº 0025/2018 ocurrido el 01.07.2018",
      "circulaciones de sentidos opuestos y dado que la normativa existente establece una condición de",
      "incompatibilidad en el establecimiento de este tipo de itinerarios se introduce la Recomendación",
      "MEDIDAS ADOPTADAS",
      "Las medidas en curso tomadas por Adif son las siguientes:",
      "Revisión y actualización de los descargadores existentes en el enclavamiento,",
      "Instalación de inhibidores de rayos para minimizar los efectos ocasionados por las tormentas eléctricas.",
      "Ante el peligro que representa el hecho de que el enclavamiento permita el establecimiento de",
      "itinerarios de entrada simultáneos, para circulaciones de sentidos opuestos, desde la Dirección Técnica",
      "de ADIF se va a acometer un proyecto de mejora en enclavamientos eléctricos, para no permitir el",
      "establecimiento de este tipo de itinerarios de entrada. El Proyecto contempla numerosos",
      "enclavamientos a nivel Red. Esta actuación se encuentra en fase de recepción de ofertas de los",
      "Puesta en servicio del nuevo enclavamiento de la estación de Pedralba.",
      "Respecto a la revisión de los hilos en servicio, dentro de las operaciones de mantenimiento de las",
      "instalaciones a las que dan servicio los cables, se toman y ajustan valores de tensión/consumo cuya",
      "tendencia/desviación es un indicador del estado en que se encuentra el cable."
    ],
    "recomendaciones": [],
    "tags": [
      "incidente",
      "factor humano",
      "señalización",
      "mantenimiento",
      "infraestructura",
      "velocidad",
      "alcoholemia",
      "cruzamiento",
      "fatal"
    ],
    "enlaces": {
      "ciaf_web": "https://www.transportes.gob.es/organos-colegiados/ciaf/informes-finales-de-sucesos-investigados",
      "pdf_local": "pdfs/2018/200421-180701-if-sn_ciaf_.pdf"
    },
    "similares": [],
    "date": "2018-07-01",
    "severity": "fatal"
  },
  {
    "id": "2018-0046/2018",
    "year": 2018,
    "expediente": "0046/2018",
    "titulo": "Informe 0046/2018",
    "tipo": "accidente",
    "tipo_suceso": "accidente",
    "gravedad": "fatal",
    "fecha_suceso": "2018-11-20",
    "ubicacion": {
      "estacion": "Barcelona Sants.",
      "provincia": "Barcelona",
      "lat": 41.3725,
      "lng": 2.1404
    },
    "entidades": [
      "ADIF",
      "Renfe Operadora",
      "Renfe Viajeros",
      "TRAM"
    ],
    "consecuencias": {
      "victimas_mortales": 0,
      "heridos": 6,
      "danos_materiales": true
    },
    "analisis": {
      "resumen": "SUBSECRETARÍA\nInvestigación del accidente\nnº 0046/2018 ocurrido el 20.11.2018\n200623-181120-IP_CIAF.doc\nRESUMEN\nEl día 20 de noviembre de 2018 a las 06:15 horas el tren de cercanías 25000, de Rodalíes de\nCataluña operado por Renfe Viajeros, procedente de Manresa y con destino San Vicenç de Calders,\ncolisiona con obstáculos (rocas), dentro del gálibo de paso libre del tren, en el p.k. 321+017 (vía 2)\nde la línea 220 de Lleida Pirineus a L´Hospitalet de Llobregat, entre las estaciones de Vacarisses (p.k.\n319+611) y Vacarisses-Torreblanca (p.k. 322+300), en la provincia de Barcelona.\nLas rocas procedían del desmoronamiento parcial (unos 20 metros) de un muro de mampostería\ncareada que protegía de la erosión el talud izquierdo de una trinchera, según el sentido de la marcha\ndel tren. Las rocas",
      "descripcion": "HECHOS INMEDIATOS DEL SUCESO ........................................................................................................... 7\n2.1.\nSUCESO ................................................................................................................................ 7\n2.1.1.\nDatos ............................................................................................................................. 7\n2.1.2.\nDescripción del suceso .................................................................................................... 8\n2.1.3.\nDecisión de abrir la investigación ................................................................................... 11\n2.2.\nCIRCUNSTANCIAS DEL SUCESO ............................................................................................ 12\n2.2.1.\nPersonal ferroviario ....................................................................................................... 12\n2.2.2.\nLos trenes y su composición .................."
    },
    "conclusiones": [
      "Investigación del accidente",
      "nº 0046/2018 ocurrido el 20.11.2018",
      "Como factor coadyuvante se considera la probable meteorización superficial del mortero de unión de",
      "los mampuestos agarre y la posible reducción del coeficiente de rozamiento entre los mampuestos y",
      "4.3.2. Causas subyacentes relacionadas con las cualificaciones del personal ferroviario y",
      "el mantenimiento del material rodante o de la infraestructura ferroviaria",
      "Como causa subyacente se determina la existencia del vertido de las aguas de drenaje de la carreta",
      "autonómica C-58 al sistema de drenaje de la vía resultando éste insuficiente y produciéndose la",
      "inundación de la vía.",
      "4.3.3. Causas raíces relacionadas con las condiciones del marco normativo y la",
      "aplicación del sistema de gestión de la seguridad",
      "Como causas raíces se consideran:",
      " La no aplicación de la ley del Sector Ferroviario (en su caso la Ley de Policía de Ferrocarriles y",
      "legislación posterior que la sustituye) respecto a la autorización de obras, mantenimiento, control,",
      "vigilancia e inspección del terreno adyacente a la vía férrea, (zona de dominio público ferroviario y",
      "zona de protección) de la carretera C-58, su cruce con el ferrocarril y su infraestructura.",
      " Insuficiencia de la ficha II Actuaciones frente a temporales de lluvia del Manual de Prevención y",
      "Gestión de Incidencias (anexo II al Plan de Contingencias) dadas las discrepancias de las",
      "predicciones con otras fuentes de datos meteorológicos y la inadecuación de las actuaciones a",
      "realizar ante el hecho acontecido"
    ],
    "recomendaciones": [
      {
        "numero": "46/2018-1",
        "texto": "Revisar la ficha II Actuaciones frente a temporales de lluvia del Manual de Prevención y Gestión de Incidencias (anexo II al Plan de Contingencias) dadas las discrepancias de las predicciones con otras fuentes de datos meteorológicos y su inadecuación ante el hecho acontecido, y los procedimientos del Sistema de Gestión de la Seguridad de",
        "implementador": ""
      }
    ],
    "tags": [
      "accidente",
      "arrollamiento",
      "colisión",
      "descarrilamiento",
      "señalización",
      "mantenimiento",
      "infraestructura",
      "velocidad",
      "alcoholemia",
      "cruzamiento",
      "incendio",
      "fatal"
    ],
    "enlaces": {
      "ciaf_web": "https://www.transportes.gob.es/organos-colegiados/ciaf/informes-finales-de-sucesos-investigados",
      "pdf_local": "pdfs/2018/200723-181120-if-sn_ciaf.pdf"
    },
    "similares": [],
    "date": "2018-11-20",
    "recommendations": [
      "Destinatario \nImplementador \nfinal \nNúmero \nRecomendación \nAgencia \nEstatal \nde \nSeguridad \nFerroviaria \n(AESF) \nAdministrador de \nInfraestructuras \nFerroviarias (ADIF) \n46/2018-1 \nRevisar la ficha II Actuaciones frente a temporales \nde lluvia del Manual de Prevención y Gestión de \nIncidencias (anexo II al Plan de Contingencias) \ndadas las discrepancias de las predicciones con \notras fuentes de datos meteorológicos y su \ninadecuación ante el hecho acontecido, y los \nprocedimientos del Sistema de Gestión de la \nSeguridad de Adif (SGS) relativos a la inspección y \nmantenimiento de la infraestructura, dada la falta \nde \nrespuesta \nante \nlos \nhechos \nconstatados \n(introducción en el trasdós del muro de agua \nprocedente de la escorrentía en superficie).",
      "Agencia \nEstatal \nde \nSeguridad \nFerroviaria \n(AESF) \nAdministrador de \nInfraestructuras \nFerroviarias (ADIF) \n46/2018-2 Revisar la aplicación de la ley del Sector Ferroviario \n(en su caso la Ley de Policía de Ferrocarriles y \nlegislación posterior que la sustituye) respecto a la \nautorización de obras, mantenimiento, control, \nvigilancia e inspección del terreno adyacente a la \nvía férrea (zona de dominio público ferroviario y \nzona de protección) de la carretera C-58, su cruce \ncon el ferrocarril y su infraestructura.",
      "Agencia \nEstatal \nde \nSeguridad \nFerroviaria \n(AESF) \nAdministrador de \nInfraestructuras \nFerroviarias (ADIF) \n46/2018-3 Identificación \nde \nlos \nmuros \nde \nsimilares \ncaracterísticas que tengan agentes externos \n(otras infraestructuras o vertidos de aguas), como \nel de este caso, que puedan llegar a comprometer \nsu estabilidad.",
      "A \nMINISTERIO \nDE FOMENTO \nSUB \n \n200623-181120-IP_CIAF.doc \n \n \n \nDestinatario \nImplementador \nfinal \nNúmero \nRecomendación \nAgencia \nEstatal \nde \nSeguridad \nFerroviaria \n(AESF) \nAdministrador"
    ],
    "severity": "fatal"
  }
]